higuard_sdk/__init__.py
higuard_sdk/api_client.py
higuard_sdk/configs.py
higuard_sdk/environment.py
higuard_sdk/error_tracker.py
higuard_sdk/fetch.py
higuard_sdk/utils.py
higuard_sdk-0.1.9.dist-info/METADATA
higuard_sdk-0.1.9.dist-info/WHEEL
higuard_sdk-0.1.9.dist-info/top_level.txt
higuard_sdk-0.1.9.dist-info/RECORD
