Metadata-Version: 2.1
Name: higuard-sdk
Version: 0.1.9
Summary: Python SDK for Error Dashboard
Home-page: https://github.com/HiQ-Apps/error_dashboard_python
Author: Derek Li
Author-email: derekli11204@gmail.com
Classifier: Programming Language :: Python :: 3
Classifier: License :: OSI Approved :: MIT License
Classifier: Operating System :: OS Independent
Requires-Python: >=3.7
Requires-Dist: certifi >=2024.7.4
Requires-Dist: charset-normalizer >=3.3.2
Requires-Dist: idna >=3.7
Requires-Dist: requests >=2.32.3
Requires-Dist: ua-parser >=0.18.0
Requires-Dist: urllib3 >=2.2.2
Requires-Dist: user-agents >=2.2.0
